{
    "offices": [
      {
          "address": "Jln Gurita",
          "id": "1",
          "image": "https://images.bisnis-cdn.com/posts/2018/10/21/851488/polestar-markas.jpg",
          "lat": -8.704841,
          "lng": 115.217854,
          "name": "MARKAS GURITA",
          "phone": "",
          "region": "denpasar"
      },
      {
          "address": "Jln Tukad Batanghari",
          "id": "2",
          "image": "https://images.bisnis-cdn.com/posts/2018/10/21/851488/polestar-markas.jpg",
          "lat": -8.680151,
          "lng": 115.230762,
          "name": "MARKAS BATANGHARI",
          "phone": "",
          "region": "denpasar"
      },
      {
          "address": "Jln Sedap Malam",
          "id": "3",
          "image": "https://images.bisnis-cdn.com/posts/2018/10/21/851488/polestar-markas.jpg",
          "lat": -8.667651,
          "lng": 115.246941,
          "name": "MARKAS SEDAP MALAM",
          "phone": "",
          "region": "denpasar"
      }
    ]
  }
